guillotina_cms/__init__.py
guillotina_cms/configure_cms.py
guillotina_cms/directives.py
guillotina_cms/events.py
guillotina_cms/exceptions.py
guillotina_cms/install.py
guillotina_cms/ordering.py
guillotina_cms/permissions.py
guillotina_cms/scripts.py
guillotina_cms/utils.py
guillotina_cms/api/__init__.py
guillotina_cms/api/components.py
guillotina_cms/api/constraint.py
guillotina_cms/api/content.py
guillotina_cms/api/following.py
guillotina_cms/api/images.py
guillotina_cms/api/indices.py
guillotina_cms/api/search.py
guillotina_cms/api/tiles.py
guillotina_cms/api/types.py
guillotina_cms/api/versioning.py
guillotina_cms/api/vocabularies.py
guillotina_cms/api/workflow.py
guillotina_cms/api/ws_edit.py
guillotina_cms/behaviors/__init__.py
guillotina_cms/behaviors/cms.py
guillotina_cms/behaviors/following.py
guillotina_cms/behaviors/image.py
guillotina_cms/behaviors/syndication.py
guillotina_cms/behaviors/tiles.py
guillotina_cms/behaviors/versioning.py
guillotina_cms/content/__init__.py
guillotina_cms/content/contraintypes.py
guillotina_cms/content/document.py
guillotina_cms/content/file.py
guillotina_cms/content/gcontent.py
guillotina_cms/content/id_generator.py
guillotina_cms/content/image.py
guillotina_cms/content/link.py
guillotina_cms/content/news.py
guillotina_cms/fields/__init__.py
guillotina_cms/fields/image.py
guillotina_cms/fields/interfaces.py
guillotina_cms/fields/richtext.py
guillotina_cms/interfaces/__init__.py
guillotina_cms/interfaces/base.py
guillotina_cms/interfaces/content.py
guillotina_cms/interfaces/events.py
guillotina_cms/interfaces/following.py
guillotina_cms/interfaces/image.py
guillotina_cms/interfaces/pubsub.py
guillotina_cms/interfaces/registry.py
guillotina_cms/interfaces/tiles.py
guillotina_cms/interfaces/versioning.py
guillotina_cms/interfaces/workflow.py
guillotina_cms/json/__init__.py
guillotina_cms/json/image.py
guillotina_cms/json/serialize_content.py
guillotina_cms/json/serialize_schema.py
guillotina_cms/subscribers/__init__.py
guillotina_cms-5.0.0a1.dist-info/LICENSE
guillotina_cms-5.0.0a1.dist-info/METADATA
guillotina_cms-5.0.0a1.dist-info/WHEEL
guillotina_cms-5.0.0a1.dist-info/entry_points.txt
guillotina_cms-5.0.0a1.dist-info/top_level.txt
guillotina_cms-5.0.0a1.dist-info/zip-safe
guillotina_cms-5.0.0a1.dist-info/RECORD
