Metadata-Version: 2.1
Name: guillotina-cms
Version: 5.0.0a1
Summary: UNKNOWN
Home-page: https://pypi.python.org/pypi/guillotina_cms
License: BSD
Platform: UNKNOWN
Classifier: Development Status :: 4 - Beta
Classifier: Programming Language :: Python :: 3.7
Classifier: Topic :: Software Development :: Libraries :: Python Modules
Requires-Dist: guillotina (>=5.0.0a6)
Requires-Dist: guillotina-dbusers (>=5.0.1)
Requires-Dist: diff-match-patch (>=20121119)
Requires-Dist: Pillow
Requires-Dist: plone.scale (>=3.0.1)
Provides-Extra: extras
Requires-Dist: guillotina-elasticsearch ; extra == 'extras'
Requires-Dist: guillotina-linkintegrity ; extra == 'extras'
